tkgridgui/SourceCode.py
tkgridgui/__init__.py
tkgridgui/_version.py
tkgridgui/color_lists.py
tkgridgui/comp_tree.py
tkgridgui/component_src_gen.py
tkgridgui/config_file.py
tkgridgui/contrast_color_Dialog.py
tkgridgui/cross_platform_fonts_Dialog.py
tkgridgui/edit_Dialog.py
tkgridgui/edit_options.py
tkgridgui/fg_bg_color_picker_Dialog.py
tkgridgui/grid_gui.py
tkgridgui/grid_notebook.py
tkgridgui/make_menu_src.py
tkgridgui/make_py_src.py
tkgridgui/maybe_save_Dialog.py
tkgridgui/menu_maker_Dialog.py
tkgridgui/named_color_picker_Dialog.py
tkgridgui/preview_win.py
tkgridgui/preview_win_widgets.py
tkgridgui/showinfo_Dialog.py
tkgridgui/src_templates.py
tkgridgui/target_tk_app_def.py
tkgridgui/tooltip.py
tkgridgui/wiq_color.py
tkgridgui/wt_select_Dialog.py
tkgridgui/examples/buttons.def
tkgridgui/examples/buttons.py
tkgridgui/examples/color_picker.def
tkgridgui/examples/color_picker_Dialog.py
tkgridgui/examples/contrast_color.def
tkgridgui/examples/contrast_color_Dialog.py
tkgridgui/examples/cross_platform_fonts.def
tkgridgui/examples/cross_platform_fonts_Dialog.py
tkgridgui/examples/example.def
tkgridgui/examples/example.py
tkgridgui/examples/full_combo.def
tkgridgui/examples/full_combo.py
tkgridgui/examples/info.def
tkgridgui/examples/info_Dialog.py
tkgridgui/examples/tree.def
tkgridgui/examples/tree.py
tkgridgui/tests/__init__.py
tkgridgui/tests/test_grid_gui.py
tkgridgui-0.0.25.dist-info/AUTHORS.rst
tkgridgui-0.0.25.dist-info/LICENSE
tkgridgui-0.0.25.dist-info/LICENSE.txt
tkgridgui-0.0.25.dist-info/METADATA
tkgridgui-0.0.25.dist-info/WHEEL
tkgridgui-0.0.25.dist-info/entry_points.txt
tkgridgui-0.0.25.dist-info/top_level.txt
tkgridgui-0.0.25.dist-info/RECORD
