Metadata-Version: 2.1
Name: tkgridgui
Version: 0.0.25
Summary: tkGridGUI builds a python Tkinter GUI graphic user interface using the grid geometry manager.
Home-page: http://tkgridgui.readthedocs.org/en/latest/
Download-URL: https://github.com/sonofeft/TkGridGUI
Author: Charlie Taylor
Author-email: cet@appliedpython.com
License: GPL-3
Keywords: tkgridgui setuptools development
Platform: any
Classifier: Development Status :: 3 - Alpha
Classifier: Operating System :: OS Independent
Classifier: Intended Audience :: Developers
Classifier: Intended Audience :: End Users/Desktop
Classifier: Topic :: Software Development :: Build Tools
Classifier: License :: OSI Approved :: GNU General Public License v3 (GPLv3)
Classifier: Programming Language :: Python :: 2
Classifier: Programming Language :: Python :: 2.7
Classifier: Programming Language :: Python :: 3
Classifier: Programming Language :: Python :: 3.5
Classifier: Programming Language :: Python :: 3.6
Classifier: Programming Language :: Python :: 3.7
License-File: LICENSE
License-File: LICENSE.txt
License-File: AUTHORS.rst
Requires-Dist: future
Requires-Dist: configparser
Provides-Extra: dev
Requires-Dist: check-manifest ; extra == 'dev'
Provides-Extra: test
Requires-Dist: coverage ; extra == 'test'
